README.md
setup.py
flask_doc/__init__.py
flask_doc/describer.py
flask_doc/gen_template.html
flask_doc/generator.py
flask_doc/loading.gif
flask_doc/utils.py
flask_doc.egg-info/PKG-INFO
flask_doc.egg-info/SOURCES.txt
flask_doc.egg-info/dependency_links.txt
flask_doc.egg-info/entry_points.txt
flask_doc.egg-info/not-zip-safe
flask_doc.egg-info/requires.txt
flask_doc.egg-info/top_level.txt