Metadata-Version: 1.0
Name: flask-doc
Version: 0.2.6
Summary: Write API document when you coding, Test your API when you press last word immediately
Home-page: https://github.com/ipconfiger/flask-apidoc
Author: Alexander.Li
Author-email: superpowerlee@gmail.com
License: GNU GENERAL PUBLIC LICENSE
Platform: UNKNOWN
